dbt_remote/__init__.py
dbt_remote/cli.py
dbt_remote/src/cli_input.py
dbt_remote/src/cli_local_config.py
dbt_remote/src/cli_params.py
dbt_remote/src/cli_schedules.py
dbt_remote/src/cli_utils.py
dbt_remote/src/dbt_server.py
dbt_remote/src/dbt_server_detector.py
dbt_remote/src/dbt_server_image.py
dbt_remote/version.py
dbt_server/Dockerfile
dbt_server/README.md
dbt_server/dbt_run_job.py
dbt_server/lib/cloud_scheduler.py
dbt_server/lib/dbt_cloud_run_job.py
dbt_server/lib/dbt_command.py
dbt_server/lib/firestore.py
dbt_server/lib/gcs.py
dbt_server/lib/logger.py
dbt_server/lib/state.py
dbt_server/requirements.txt
dbt_server/server.py
dbt_server/version.py
gcp_dbt_remote-0.4.6.dist-info/LICENSE
gcp_dbt_remote-0.4.6.dist-info/METADATA
gcp_dbt_remote-0.4.6.dist-info/WHEEL
gcp_dbt_remote-0.4.6.dist-info/entry_points.txt
gcp_dbt_remote-0.4.6.dist-info/RECORD
