Metadata-Version: 2.1
Name: gcp_dbt_remote
Version: 0.4.6
Summary: cli to run dbt commands on GCP Cloud Run Jobs using dbt-server.
Author: emma.galliere
Author-email: emma.galliere@artefact.com
Requires-Python: >=3.10,<3.12
Classifier: Programming Language :: Python :: 3
Classifier: Programming Language :: Python :: 3.10
Classifier: Programming Language :: Python :: 3.11
Requires-Dist: click-aliases (>=1,<2)
Requires-Dist: cron-descriptor (>=1,<2)
Requires-Dist: dbt-bigquery (>=1.7.0,<1.8.0)
Requires-Dist: fastapi (>=0,<1)
Requires-Dist: google-cloud-build (>=3,<4)
Requires-Dist: google-cloud-firestore (>=2,<3)
Requires-Dist: google-cloud-iam (>=2,<3)
Requires-Dist: google-cloud-logging (>=3,<4)
Requires-Dist: google-cloud-run (>=0,<1)
Requires-Dist: google-cloud-scheduler (>=2,<3)
Requires-Dist: httpx (>=0,<1)
Requires-Dist: pyfakefs (>=5,<6)
Requires-Dist: pytest (>=7,<8)
Requires-Dist: python-multipart (>=0,<1)
Requires-Dist: requests-mock (>=1,<2)
Requires-Dist: termcolor (>=2,<3)
Requires-Dist: uvicorn (>=0,<1)
